{
    "player_id": "00002219700507X",
    "name": "Ｍ．スミス",
    "name_kana": "MARK SMITH",
    "profile": {
        "投打": "右投右打",
        "身長／体重": "190cm／107kg",
        "生年月日": "1970年5月7日",
        "経歴": "サザンカリフォルニア大 - オリオールズ - パイレーツ",
        "ドラフト": ""
    },
    "url": "https://npb.jp/bis/players/11613888.html",
    "stats": [
        {
            "年度": 1999.0,
            "所属球団": "ヤクルト",
            "試合": 98,
            "打席": 325,
            "打数": 293,
            "得点": 38,
            "安打": 76,
            "二塁打": 11,
            "三塁打": 1,
            "本塁打": 20,
            "塁打": 149,
            "打点": 55,
            "盗塁": 3,
            "盗塁刺": 1,
            "犠打": 1,
            "犠飛": 2,
            "四球": 22,
            "死球": 7,
            "三振": 83,
            "併殺打": 4,
            "打率": 0.259,
            "長打率": 0.509,
            "出塁率": 0.324,
            "stats_type": "batting"
        }
    ]
}