{
    "player_id": "000012193906290",
    "name": "植田　征作",
    "name_kana": "うえだ・せいさく",
    "profile": {
        "投打": "左投左打",
        "身長／体重": "177cm／70kg",
        "生年月日": "1939年6月29日",
        "経歴": "下関商 - 東洋紡岩国",
        "ドラフト": ""
    },
    "url": "https://npb.jp/bis/players/81183823.html",
    "stats": [
        {
            "年度": 1961.0,
            "所属球団": "西　鉄",
            "試合": 3,
            "打席": 3,
            "打数": 3,
            "得点": 0,
            "安打": 1,
            "二塁打": 0,
            "三塁打": 0,
            "本塁打": 0,
            "塁打": 1,
            "打点": 0,
            "盗塁": 1,
            "盗塁刺": 0,
            "犠打": 0,
            "犠飛": 0,
            "四球": 0,
            "死球": 0,
            "三振": 1,
            "併殺打": 0,
            "打率": 0.333,
            "長打率": 0.333,
            "出塁率": NaN,
            "stats_type": "batting"
        },
        {
            "年度": 1962.0,
            "所属球団": "西　鉄",
            "試合": 1,
            "打席": 1,
            "打数": 1,
            "得点": 0,
            "安打": 0,
            "二塁打": 0,
            "三塁打": 0,
            "本塁打": 0,
            "塁打": 0,
            "打点": 0,
            "盗塁": 0,
            "盗塁刺": 0,
            "犠打": 0,
            "犠飛": 0,
            "四球": 0,
            "死球": 0,
            "三振": 1,
            "併殺打": 0,
            "打率": 0.0,
            "長打率": 0.0,
            "出塁率": ".000",
            "stats_type": "batting"
        },
        {
            "年度": 1964.0,
            "所属球団": "西　鉄",
            "試合": 8,
            "打席": 16,
            "打数": 14,
            "得点": 1,
            "安打": 2,
            "二塁打": 0,
            "三塁打": 0,
            "本塁打": 1,
            "塁打": 5,
            "打点": 3,
            "盗塁": 0,
            "盗塁刺": 0,
            "犠打": 1,
            "犠飛": 0,
            "四球": 1,
            "死球": 0,
            "三振": 3,
            "併殺打": 2,
            "打率": 0.143,
            "長打率": 0.357,
            "出塁率": ".200",
            "stats_type": "batting"
        },
        {
            "年度": 1965.0,
            "所属球団": "西　鉄",
            "試合": 57,
            "打席": 62,
            "打数": 56,
            "得点": 4,
            "安打": 10,
            "二塁打": 1,
            "三塁打": 0,
            "本塁打": 0,
            "塁打": 11,
            "打点": 10,
            "盗塁": 0,
            "盗塁刺": 1,
            "犠打": 1,
            "犠飛": 0,
            "四球": 4,
            "死球": 1,
            "三振": 5,
            "併殺打": 1,
            "打率": 0.179,
            "長打率": 0.196,
            "出塁率": ".246",
            "stats_type": "batting"
        },
        {
            "年度": 1966.0,
            "所属球団": "西　鉄",
            "試合": 36,
            "打席": 35,
            "打数": 32,
            "得点": 0,
            "安打": 9,
            "二塁打": 2,
            "三塁打": 0,
            "本塁打": 0,
            "塁打": 11,
            "打点": 4,
            "盗塁": 0,
            "盗塁刺": 0,
            "犠打": 0,
            "犠飛": 1,
            "四球": 2,
            "死球": 0,
            "三振": 7,
            "併殺打": 1,
            "打率": 0.281,
            "長打率": 0.344,
            "出塁率": ".324",
            "stats_type": "batting"
        },
        {
            "年度": 1967.0,
            "所属球団": "西　鉄",
            "試合": 62,
            "打席": 60,
            "打数": 53,
            "得点": 1,
            "安打": 9,
            "二塁打": 3,
            "三塁打": 1,
            "本塁打": 0,
            "塁打": 14,
            "打点": 10,
            "盗塁": 0,
            "盗塁刺": 0,
            "犠打": 0,
            "犠飛": 2,
            "四球": 5,
            "死球": 0,
            "三振": 14,
            "併殺打": 0,
            "打率": 0.17,
            "長打率": 0.264,
            "出塁率": ".241",
            "stats_type": "batting"
        }
    ]
}