{
    "player_id": "00002219490409X",
    "name": "Ｓ．ユーイング",
    "name_kana": "SAM EWING",
    "profile": {
        "投打": "右投左打",
        "身長／体重": "190cm／93kg",
        "生年月日": "1949年4月9日",
        "経歴": "テネシー大 - ホワイトソックス - ブルージェイズ",
        "ドラフト": ""
    },
    "url": "https://npb.jp/bis/players/81983848.html",
    "stats": [
        {
            "年度": 1979.0,
            "所属球団": "日本ハム",
            "試合": 119,
            "打席": 449,
            "打数": 416,
            "得点": 41,
            "安打": 119,
            "二塁打": 20,
            "三塁打": 2,
            "本塁打": 15,
            "塁打": 188,
            "打点": 65,
            "盗塁": 2,
            "盗塁刺": 0,
            "犠打": 0,
            "犠飛": 4,
            "四球": 29,
            "死球": 0,
            "三振": 77,
            "併殺打": 11,
            "打率": 0.286,
            "長打率": 0.452,
            "出塁率": ".333",
            "stats_type": "batting"
        }
    ]
}